sphinx_json_schema/__init__.py
sphinx_json_schema/compat.py
sphinx_json_schema/directive.py
sphinx_json_schema/loader.py
sphinx_json_schema/mergers.py
sphinx_json_schema/version.py
tests/__init__.py
tests/test_allof.py
tests/test_merge.py
tests/test_not.py
tests/test_oneof.py
sphinx_json_schema-0.2.dist-info/LICENSE.rst
sphinx_json_schema-0.2.dist-info/METADATA
sphinx_json_schema-0.2.dist-info/WHEEL
sphinx_json_schema-0.2.dist-info/top_level.txt
sphinx_json_schema-0.2.dist-info/zip-safe
sphinx_json_schema-0.2.dist-info/RECORD
