Metadata-Version: 2.1
Name: sphinx-json-schema
Version: 0.2
Summary: JSON Schema renderer for Sphinx
Home-page: https://github.com/tkhyn/sphinx-json-schema/
Author: Thomas Khyn
Author-email: thomas@ksytek.com
License: UNKNOWN
Keywords: sphinx,json,schema
Platform: UNKNOWN
Classifier: Programming Language :: Python :: 3
Classifier: Development Status :: 5 - Production/Stable
Classifier: License :: OSI Approved :: MIT License
Classifier: Environment :: Plugins
Classifier: Framework :: Sphinx :: Extension
Classifier: Intended Audience :: Developers
Classifier: Topic :: Software Development :: Documentation
Classifier: Topic :: Documentation :: Sphinx
Requires-Dist: sphinx
Requires-Dist: jsonpointer
